orbax/__init__.py
orbax/conftest.py
orbax/checkpoint/README.md
orbax/checkpoint/__init__.py
orbax/checkpoint/abstract_checkpointer.py
orbax/checkpoint/aggregate_handlers.py
orbax/checkpoint/array_checkpoint_handler.py
orbax/checkpoint/async_checkpoint_handler.py
orbax/checkpoint/async_checkpointer.py
orbax/checkpoint/checkpoint_handler.py
orbax/checkpoint/checkpoint_manager.py
orbax/checkpoint/checkpoint_utils.py
orbax/checkpoint/checkpoint_utils_test.py
orbax/checkpoint/checkpointer.py
orbax/checkpoint/future.py
orbax/checkpoint/json_checkpoint_handler.py
orbax/checkpoint/json_checkpoint_handler_test.py
orbax/checkpoint/lazy_utils.py
orbax/checkpoint/msgpack_utils.py
orbax/checkpoint/orbax_checkpoint.ipynb
orbax/checkpoint/pytree_checkpoint_handler.py
orbax/checkpoint/test_utils.py
orbax/checkpoint/transform_utils.py
orbax/checkpoint/transform_utils_test.py
orbax/checkpoint/type_handlers.py
orbax/checkpoint/utils.py
orbax/checkpoint/utils_test.py
orbax-0.1.7.dist-info/LICENSE
orbax-0.1.7.dist-info/WHEEL
orbax-0.1.7.dist-info/METADATA
orbax-0.1.7.dist-info/RECORD
