Metadata-Version: 2.1
Name: orbax
Version: 0.1.7
Summary: Orbax
Keywords: JAX machine learning
Author-email: Orbax Authors <orbax-dev@google.com>
Requires-Python: >=3.8
Classifier: Development Status :: 4 - Beta
Classifier: Intended Audience :: Developers
Classifier: Intended Audience :: Science/Research
Classifier: License :: OSI Approved :: Apache Software License
Classifier: Programming Language :: Python
Classifier: Topic :: Scientific/Engineering :: Artificial Intelligence
Requires-Dist: absl-py
Requires-Dist: cached_property
Requires-Dist: importlib_resources
Requires-Dist: typing_extensions
Requires-Dist: msgpack
Requires-Dist: etils
Requires-Dist: jax >= 0.4.6
Requires-Dist: jaxlib
Requires-Dist: numpy
Requires-Dist: pyyaml
Requires-Dist: tensorstore >= 0.1.20
Requires-Dist: nest_asyncio
Requires-Dist: pytest ; extra == "dev"
Requires-Dist: pytest-xdist ; extra == "dev"
Requires-Dist: flax ; extra == "dev"
Project-URL: homepage, http://github.com/google/orbax
Project-URL: repository, http://github.com/google/orbax
Provides-Extra: dev
